README.md
ddosa.py
setup.py
dda_ddosa.egg-info/PKG-INFO
dda_ddosa.egg-info/SOURCES.txt
dda_ddosa.egg-info/dependency_links.txt
dda_ddosa.egg-info/top_level.txt