Metadata-Version: 1.0
Name: dda-ddosa
Version: 1.0
Summary: ddosa
Home-page: UNKNOWN
Author: V.S.
Author-email: UNKNOWN
License: UNKNOWN
Platform: UNKNOWN
